Metadata-Version: 2.1
Name: TextTools-poo2
Version: 0.1.0
Author: Marcos, Anna
Author-email: annabeatriz_2019@outlook.com
Classifier: Programming Language :: Python :: 3
Classifier: License :: OSI Approved :: MIT License
Classifier: Operating System :: OS Independent
Requires-Python: >=3.6
Requires-Dist: Click
